nonebot_plugin_xingzuo/__init__.py
nonebot_plugin_xingzuo-1.0.3.dist-info/LICENSE
nonebot_plugin_xingzuo-1.0.3.dist-info/METADATA
nonebot_plugin_xingzuo-1.0.3.dist-info/WHEEL
nonebot_plugin_xingzuo-1.0.3.dist-info/RECORD
