Metadata-Version: 2.1
Name: nonebot-plugin-xingzuo
Version: 1.0.3
Summary: 一个nonebot插件，可以查询星座运势
License: MIT
Author: mengxinyuan
Author-email: 1648576390@qq.com
Requires-Python: >=3.8,<4.0
Classifier: License :: OSI Approved :: MIT License
Classifier: Programming Language :: Python :: 3
Classifier: Programming Language :: Python :: 3.8
Classifier: Programming Language :: Python :: 3.9
Classifier: Programming Language :: Python :: 3.10
Classifier: Programming Language :: Python :: 3.11
Requires-Dist: httpx (==0.23.0)
Requires-Dist: nonebot2 (>=2.0.0rc1,<3.0.0)
